  <page>
    <title>Animal (disambiguation)</title>
    <ns>0</ns>
    <id>679</id>
    <revision>
      <id>942911856</id>
      <parentid>942901788</parentid>
      <timestamp>2020-02-27T17:14:20Z</timestamp>
      <contributor>
        <username>Fyrael</username>
        <id>6675779</id>
      </contributor>
      <comment>/* Professional wrestlers */</comment>
      <model>wikitext</model>
      <format>text/x-wiki</format>
      <text xml:space="preserve">{{wiktionary|animal}}
An '''[[animal]]''' is a multicellular, eukaryotic organism of the kingdom Animalia or Metazoa.

'''Animal''' or '''Animals''' or '''The Animal''' may also refer to:

{{TOC right}}
==People==
* [[The Animal (nickname)]], a set index of people nicknamed &quot;The Animal&quot; or &quot;Animal&quot;

===Professional wrestlers===
* [[Road Warrior Animal]] (born 1960), commonly shortened to &quot;Animal&quot;, the best-known ring persona of Joe Laurinaitis
* [[Animal Hamaguchi]] (born 1947), ring name of Japanese retired wrestler Heigo Hamaguchi
* [[George Steele]] (1937–2017), American retired professional wrestler, author and actor known as &quot;The Animal&quot;
* [[Dave Bautista]] (born 1969), American retired professional wrestler whose nickname is &quot;The Animal&quot;

==Books and publications==
* [[Animal (book)|''Animal'' (book)]], full title ''Animal: The Definitive Visual Guide to The World's WildLife'', a 2003 non-fiction book by David Burnie and several co-authors
* ''Animal'', 2012 novel by [[K'wan Foye]]
* [[Animal (journal)|''Animal'' (journal)]], full title: ''Animal: An International Journal of Animal Bioscience'', British academic journal
*[[Animals (novel)|''Animals'' (novel)]], a 2014 novel by Emma Jane Unsworth

==Film and television==

===Film===
* [[Animal (1977 film)|''Animal'' (1977 film)]], French film (''L'Animal'') starring Jean-Paul Belmondo and Raquel Welch
* [[Animal (2001 film)|''Animal'' (2001 film)]], Argentine comedy film by Sergio Bizzio with Carlos Roffé
* [[Animal (2005 film)|''Animal'' (2005 film)]], US direct-to-video action drama film starring Ving Rhames and Terrance Howard
* [[Animal (2014 film)|''Animal'' (2014 film)]], US horror film starring Keke Palmer
* [[Animals (2003 film)|''Animals'' (2003 film)]], stand-up show written and performed by Ricky Gervais
* [[Animals (2014 film)|''Animals'' (2014 film)]], UK drama film written by and starring David Dastmalchian
* [[Animals (2017 film)|''Animals'' (2017 film)]], German film
* [[Animals (2019 film)|''Animals'' (2019 film)]], Australian film
* ''[[The Animal]]'', 2001 US comedy film featuring Rob Schneider
* [[The Animals (film)|''The Animals'' (film)]], 2012 Filipino coming-of-age film by Gino M. Santos

===Television===
* [[Animals (U.S. TV series)|''Animals'' (U.S. TV series)]], a 2016 American animated television series
* [[Animals (South Korean TV series)|''Animals'' (South Korean TV series)]], a South Korean TV series
* [[Animals (The Goodies)|&quot;Animals&quot; (''The Goodies'')]], television series episode
* &quot;Animals&quot;, an [[List of Men Behaving Badly episodes#ep4|episode of ''Men Behaving Badly'']]
* &quot;Animals&quot;, an episode of ''[[Off the Air (TV series)#ep1|Off the Air]]''
* &quot;Animals&quot;, an [[List of The Vicar of Dibley episodes#ep6|episode of ''The Vicar of Dibley'']]
* [[Animal (audio drama)|''Animal'' (audio drama)]], an audio drama based on the television series ''Doctor Who''

===Characters===
* [[Animal (Muppet)]], a character from the television series ''The Muppet Show''
* Animal, a character in the television series ''[[Takeshi's Castle]]''
* Animal, played by Ken Hudson Campbell, a character on the TV sitcom ''[[Herman's Head]]''

==Music==
* [[The Animals]], a British rock band
* [[A.N.I.M.A.L.]], an Argentinian heavy metal band

===Albums===
* [[Animal (Animosity album)|''Animal'' (Animosity album)]], 2007
* [[Animal (Kesha album)|''Animal'' (Kesha album)]], 2010
* [[Animal (Motor Ace album)|''Animal'' (Motor Ace album)]], 2005
* [[Animals (Pink Floyd album)|''Animals'' (Pink Floyd album)]], 1977
* [[Animals (This Town Needs Guns album)|''Animals'' (This Town Needs Guns album)]], 2008
* [[Animals (EP)|''Animals'' (EP)]] by Ryan Starx, 2013
* [[The Animals (American album)|''The Animals'' (American album)]], by The Animals, 1964
* [[The Animals (British album)|''The Animals'' (British album)]], by The Animals, 1964
* ''Animal'', a 2009 album by [[AutoKratz]]
* ''Animal'', a 1988 album by [[the Bar-Kays]]
* ''Animal'', a 2013 album by [[Berlin (band)|Berlin]]
* ''Animal'', a 2008 album by [[Far East Movement]]
* ''Animal!'', a 2008 album by [[Margot &amp; the Nuclear So and So's]]

===Songs===
{{redirect-distinguish|Animal (song)|Animal song|The Animal Song}}
* [[Animal (Álvaro Soler song)|&quot;Animal&quot; (Álvaro Soler song)]], 2017
* [[Animal (Conor Maynard song)|&quot;Animal&quot; (Conor Maynard song)]], 2013
* [[Animal (Def Leppard song)|&quot;Animal&quot; (Def Leppard song)]], 1987
* [[Animal (Jebediah song)|&quot;Animal&quot; (Jebediah song)]]
* [[Animal (Juvenile song)|&quot;Animal&quot; (Juvenile song)]]
* [[Animal (Kesha song)|&quot;Animal&quot; (Kesha song)]]
* [[Animal (Miike Snow song)|&quot;Animal&quot; (Miike Snow song)]], 2009
* [[Animal (Neon Trees song)|&quot;Animal&quot; (Neon Trees song)]], 2010
* [[Animal (Pearl Jam song)|&quot;Animal&quot; (Pearl Jam song)]], 1994
* [[Animal (R.E.M. song)|&quot;Animal&quot; (R.E.M. song)]]
* [[Animal (Troye Sivan song)|&quot;Animal&quot; (Troye Sivan song)]], 2018
* [[Animal (R.I.O. song)|&quot;Animal&quot; (R.I.O. song)]], 2011
* [[Animals (Kevin Ayers song)|&quot;Animals&quot; (Kevin Ayers song)]], 1980
* &quot;[[Animal (Fuck Like a Beast)]]&quot;, by W.A.S.P.
* [[Animals (Maroon 5 song)|&quot;Animals&quot; (Maroon 5 song)]], 2014
* [[Animals (Martin Garrix song)|&quot;Animals&quot; (Martin Garrix song)]], 2013
* [[Animals (Muse song)|&quot;Animals&quot; (Muse song)]], 2012
* [[Animals (Nickelback song)|&quot;Animals&quot; (Nickelback song)]], 2005
* [[The Animal (Disturbed song)|&quot;The Animal&quot; (Disturbed song)]], 2010
* &quot;Animal&quot;, by Against Me! from ''[[New Wave (Against Me! album)|New Wave]]''
* &quot;Animal&quot;, by Ani DiFranco from ''[[Educated Guess]]''
* &quot;Animal&quot;, by Aurora from ''[[A Different Kind of Human (Step 2)]]''
* &quot;Animal&quot;, by Black Light Burns from ''[[Cruel Melody]]''
* &quot;Animal&quot;, by Ellie Goulding from ''[[Lights (Ellie Goulding album)|Lights]]''
* &quot;Animal&quot;, by Karen O and the Kids from ''[[Where the Wild Things Are (soundtrack)|Where the Wild Things Are]]''
* &quot;Animal&quot;, by Kat DeLuna from ''[[9 Lives (Kat DeLuna album)|9 Lives]]''
* &quot;Animal&quot;, by Mindless Self Indulgence from ''[[If (Mindless Self Indulgence album)|If]]''
* &quot;Animal&quot;, by [[Mudmen]] from ''Overrated''
* &quot;Animal&quot; by Subhumans from ''[[Demolition War]]''
* &quot;Animal&quot;, by [[Sunhouse (band)|Sunhouse]] from ''Crazy On The Weekend''
* &quot;Animal&quot;, by the Kinks from ''[[To the Bone (The Kinks album)|To the Bone]]''
* &quot;Animal&quot;, by Toto from ''[[Past to Present 1977–1990]]''
* &quot;Animals&quot;, by CocoRosie from ''[[The Adventures of Ghosthorse and Stillborn]]''
* &quot;Animals&quot;, by Coldplay as one of the B-sides for &quot;[[Clocks (song)|Clocks]]&quot;
* &quot;Animals&quot;, by Dead Poetic from ''[[Vices (Dead Poetic album)|Vices]]''
* &quot;Animals&quot;, by Talking Heads from ''[[Fear of Music]]''
* &quot;Animals&quot;, by the End from ''[[Elementary (The End album)|Elementary]]''
* &quot;Animals&quot;, by Todrick Hall featuring Matt Bloyd from ''[[Forbidden (Todrick Hall album)|Forbidden]]''
* &quot;The Animal&quot;, by Steve Vai from ''[[Passion and Warfare]]''

==Other==
* [[ANIMAL (computer worm)]], an early self-replicating computer program
* [[ANIMAL (image processing)]], an interactive software environment for image processing
* [[Animal (clothing)]], a sportswear retailer and brand based in the United Kingdom
* [[Animals (Israeli organization)]],  an animal rights group based in Israel

==See also==
* ''[[Animals, Animals, Animals]]'', an American educational television series (1976–1981)
* [[Animalia (disambiguation)]]
* [[Animalism (disambiguation)]]

{{Disambiguation}}</text>
      <sha1>tfvoko1kg8ew4gcfheomv7hjhnj7zkm</sha1>
    </revision>
  </page>
