  <page>
    <title>Optical audio disc</title>
    <ns>0</ns>
    <id>2964</id>
    <revision>
      <id>931517312</id>
      <parentid>826781138</parentid>
      <timestamp>2019-12-19T09:54:30Z</timestamp>
      <contributor>
        <username>DocWatson42</username>
        <id>38455</id>
      </contributor>
      <comment>/* Audio CDs */Performed minor cleanup.</comment>
      <model>wikitext</model>
      <format>text/x-wiki</format>
      <text xml:space="preserve">An '''audio optical disc''' is an [[optical disc]] that stores sound information such as music or speech.

It may specifically refer to:

{{tocright}}
==Audio CDs==
* [[Compact disc]] (CD), an optical disc used to store digital data (700 MB storage)
** [[Compact Disc Digital Audio]] (CD-DA), a CD that contains PCM encoded digital audio in the original &quot;Red Book&quot; CD-DA format
** [[5.1 Music Disc]], an extension to the Red Book standard that uses DTS Coherent Acoustics 5.1 surround sound
** [[Compressed audio optical disc]], an optical disc storing MP3s and other compressed audio files as data, rather than in the Red Book format

==Audio DVDs==

*[[DVD]], 4 GB single layer, 8 GB double layer storage
** [[DVD-Audio]], a DVD that plays audio
** [[Super Audio CD]] (SACD), a format which competes with DVD-Audio

==Audio Blu-rays==

*[[Blu-ray]], 25 GB single layer, 50 GB double layer
** [[BD-Audio]], a Blu-ray disc that is capable of audio-only playback

==See also==
*CD-4 or [[Compatible discrete four-channel sound]], a variety of quadrophonic audio for vinyl records

{{disambiguation}}</text>
      <sha1>drnh7a68y48a1l3dujesj9bq2xcgdfk</sha1>
    </revision>
  </page>
